README.md
grubhub/__init__.py
grubhub/client.py
grubhub-0.1.0.dist-info/LICENSE
grubhub-0.1.0.dist-info/WHEEL
grubhub-0.1.0.dist-info/METADATA
grubhub-0.1.0.dist-info/RECORD
