Metadata-Version: 2.1
Name: grubhub
Version: 0.1.0
Summary: A quick wrapper around GrubHub's API, to fetch account and order information.
Home-page: https://github.com/jlumbroso/grubhub
License: LGPL-3.0-or-later
Keywords: grubhub
Author: Jérémie Lumbroso
Author-email: lumbroso@cs.princeton.edu
Requires-Python: >=3.8,<4.0
Classifier: Development Status :: 3 - Alpha
Classifier: License :: OSI Approved :: GNU Lesser General Public License v3 or later (LGPLv3+)
Classifier: Programming Language :: Python :: 3
Classifier: Programming Language :: Python :: 3.8
Classifier: Programming Language :: Python :: 3.9
Classifier: Topic :: Software Development :: Libraries :: Python Modules
Requires-Dist: bs4 (>=0.0.1,<0.0.2)
Requires-Dist: python-dateutil (>=2.8.1,<3.0.0)
Requires-Dist: pyyaml (>=5.3.1,<6.0.0)
Requires-Dist: requests (>=2.26.0,<3.0.0)
Requires-Dist: user-agent (>=0.1.10,<0.2.0)
Project-URL: Repository, https://github.com/jlumbroso/grubhub
